deepctr/__init__.py
deepctr/feature_column.py
deepctr/inputs.py
deepctr/utils.py
deepctr/contrib/__init__.py
deepctr/contrib/rnn.py
deepctr/contrib/rnn_v2.py
deepctr/contrib/utils.py
deepctr/estimator/__init__.py
deepctr/estimator/feature_column.py
deepctr/estimator/inputs.py
deepctr/estimator/utils.py
deepctr/estimator/models/__init__.py
deepctr/estimator/models/afm.py
deepctr/estimator/models/autoint.py
deepctr/estimator/models/ccpm.py
deepctr/estimator/models/dcn.py
deepctr/estimator/models/deepfm.py
deepctr/estimator/models/fibinet.py
deepctr/estimator/models/fnn.py
deepctr/estimator/models/fwfm.py
deepctr/estimator/models/nfm.py
deepctr/estimator/models/pnn.py
deepctr/estimator/models/wdl.py
deepctr/estimator/models/xdeepfm.py
deepctr/layers/__init__.py
deepctr/layers/activation.py
deepctr/layers/core.py
deepctr/layers/interaction.py
deepctr/layers/normalization.py
deepctr/layers/sequence.py
deepctr/layers/utils.py
deepctr/models/__init__.py
deepctr/models/afm.py
deepctr/models/autoint.py
deepctr/models/ccpm.py
deepctr/models/dcn.py
deepctr/models/deepfm.py
deepctr/models/dien.py
deepctr/models/din.py
deepctr/models/dsin.py
deepctr/models/fgcnn.py
deepctr/models/fibinet.py
deepctr/models/flen.py
deepctr/models/fnn.py
deepctr/models/fwfm.py
deepctr/models/mlr.py
deepctr/models/nfm.py
deepctr/models/nincnn.py
deepctr/models/nncnn.py
deepctr/models/nncnn10.py
deepctr/models/nncnn11.py
deepctr/models/nncnn12.py
deepctr/models/nncnn13.py
deepctr/models/nncnn14.py
deepctr/models/nncnn15.py
deepctr/models/nncnn2.py
deepctr/models/nncnn3.py
deepctr/models/nncnn4.py
deepctr/models/nncnn5.py
deepctr/models/nncnn6.py
deepctr/models/nncnn7.py
deepctr/models/nncnn8.py
deepctr/models/nncnn9.py
deepctr/models/npcnn.py
deepctr/models/npcnn2.py
deepctr/models/npcnn3.py
deepctr/models/npcnn4.py
deepctr/models/npcnn5.py
deepctr/models/npcnn6.py
deepctr/models/npcnn7.py
deepctr/models/npcnn8.py
deepctr/models/npcnn9.py
deepctr/models/onn.py
deepctr/models/pnn.py
npcnn-0.3.dist-info/LICENSE
npcnn-0.3.dist-info/METADATA
npcnn-0.3.dist-info/WHEEL
npcnn-0.3.dist-info/top_level.txt
npcnn-0.3.dist-info/RECORD
